pyam/__init__.py
pyam/_compare.py
pyam/_debiasing.py
pyam/_ops.py
pyam/_style.py
pyam/aggregation.py
pyam/compute.py
pyam/core.py
pyam/exceptions.py
pyam/figures.py
pyam/filter.py
pyam/iiasa.py
pyam/index.py
pyam/ixmp4.py
pyam/logging.yaml
pyam/netcdf.py
pyam/plotting.py
pyam/run_control.py
pyam/slice.py
pyam/statistics.py
pyam/str.py
pyam/testing.py
pyam/time.py
pyam/timeseries.py
pyam/unfccc.py
pyam/units.py
pyam/utils.py
pyam/validation.py
pyam/worldbank.py
pyam_iamc-3.2.0.dist-info/METADATA
pyam_iamc-3.2.0.dist-info/WHEEL
pyam_iamc-3.2.0.dist-info/licenses/AUTHORS.rst
pyam_iamc-3.2.0.dist-info/licenses/LICENSE
pyam_iamc-3.2.0.dist-info/licenses/NOTICE.md
pyam_iamc-3.2.0.dist-info/RECORD
