Metadata-Version: 2.4
Name: pyam-iamc
Version: 3.2.0
Summary: Analysis & visualization of integrated-assessment scenarios
License-Expression: Apache-2.0
License-File: AUTHORS.rst
License-File: LICENSE
License-File: NOTICE.md
Author: Matthew Gidden
Author-email: gidden@iiasa.ac.at
Requires-Python: >=3.10, <3.14
Classifier: Development Status :: 5 - Production/Stable
Classifier: Intended Audience :: Science/Research
Classifier: Topic :: Scientific/Engineering
Classifier: Natural Language :: English
Classifier: Programming Language :: Python
Requires-Dist: Pint (>=0.13)
Requires-Dist: PyYAML (>=6.0.1)
Requires-Dist: XlsxWriter (>=3.0.3)
Requires-Dist: iam-units (>=2020.4.21)
Requires-Dist: ixmp4 (>=0.13.0)
Requires-Dist: matplotlib (>=3.6.0)
Requires-Dist: numpy (>=1.26.0)
Requires-Dist: openpyxl (>=3.1.2)
Requires-Dist: pandas (>=2.1.2)
Requires-Dist: requests (>2.27.1)
Requires-Dist: scipy (>=1.10.0)
Requires-Dist: seaborn (>=0.11)
Requires-Dist: wquantiles (>=0.6)
Project-URL: Documentation, https://pyam-iamc.readthedocs.io
